JavaScriptNU/__init__.py
javascriptnu-0.0.2.dist-info/licenses/LICENSE
javascriptnu-0.0.2.dist-info/METADATA
javascriptnu-0.0.2.dist-info/WHEEL
javascriptnu-0.0.2.dist-info/top_level.txt
javascriptnu-0.0.2.dist-info/RECORD
