Metadata-Version: 2.4
Name: JavaScriptNU
Version: 0.0.2
Summary: JavaScript syntax in Python
Author: Iven Boxem
License-File: LICENSE
Dynamic: author
Dynamic: description
Dynamic: description-content-type
Dynamic: license-file
Dynamic: summary
